rtl/moola_decode.sv
//=============================================================================
// Project      : Moola-V (MR5) Core
// File Name    : moola_decode.sv
// Description  : Instruction Decode Stage, Immediate Generator & Control Unit
//=============================================================================

`timescale 1ns / 1ps

module moola_decode (
  // Instruction Inputs
  input  logic [31:0]             id_pc,
  input  logic [31:0]             id_pc_plus_4,
  input  logic [31:0]             id_inst,

  // Register File Read Interface
  input  logic [31:0]             rf_rs1_data,
  input  logic [31:0]             rf_rs2_data,
  output logic [4:0]              rf_rs1_addr,
  output logic [4:0]              rf_rs2_addr,

  // Decoded Control & Data Outputs to ID/EX
  output logic [31:0]             dec_pc,
  output logic [31:0]             dec_rs1_data,
  output logic [31:0]             dec_rs2_data,
  output logic [4:0]              dec_rs1_addr,
  output logic [4:0]              dec_rs2_addr,
  output logic [4:0]              dec_rd_addr,
  output logic [31:0]             dec_imm,
  output moola_pkg::alu_op_e      dec_alu_op,
  output moola_pkg::alu_src_a_e   dec_alu_src_a,
  output moola_pkg::alu_src_b_e   dec_alu_src_b,
  output moola_pkg::branch_type_e dec_branch_type,
  output logic                    dec_mem_read,
  output logic                    dec_mem_write,
  output logic                    dec_reg_write,
  output moola_pkg::wb_sel_e      dec_wb_sel
);
  import moola_pkg::*;

  // Raw Field Unpacking
  logic [6:0]  opcode;
  logic [4:0]  rd_raw;
  logic [2:0]  funct3;
  logic [4:0]  rs1_raw;
  logic [4:0]  rs2_raw;
  logic [6:0]  funct7;
  logic [31:0] imm;

  logic [4:0]  rs1_valid_addr;
  logic [4:0]  rs2_valid_addr;
  logic [4:0]  rd_valid_addr;

  assign opcode  = id_inst[6:0];
  assign rd_raw  = id_inst[11:7];
  assign funct3  = id_inst[14:12];
  assign rs1_raw = id_inst[19:15];
  assign rs2_raw = id_inst[24:20];
  assign funct7  = id_inst[31:25];

  // Source & Destination Register Qualification
  always_comb begin
    case (opcode)
      OPCODE_OP: begin
        rs1_valid_addr = rs1_raw;
        rs2_valid_addr = rs2_raw;
        rd_valid_addr  = rd_raw;
      end

      OPCODE_OP_IMM,
      OPCODE_LOAD,
      OPCODE_JALR: begin
        rs1_valid_addr = rs1_raw;
        rs2_valid_addr = 5'd0;
        rd_valid_addr  = rd_raw;
      end

      OPCODE_STORE: begin
        rs1_valid_addr = rs1_raw;
        rs2_valid_addr = rs2_raw;
        rd_valid_addr  = 5'd0; // S-Type has no rd
      end

      OPCODE_BRANCH: begin
        rs1_valid_addr = rs1_raw;
        rs2_valid_addr = rs2_raw;
        rd_valid_addr  = 5'd0; // B-Type has no rd
      end

      OPCODE_LUI,
      OPCODE_AUIPC,
      OPCODE_JAL: begin
        rs1_valid_addr = 5'd0;
        rs2_valid_addr = 5'd0;
        rd_valid_addr  = rd_raw;
      end

      default: begin
        rs1_valid_addr = 5'd0;
        rs2_valid_addr = 5'd0;
        rd_valid_addr  = 5'd0;
      end
    endcase
  end

  assign rf_rs1_addr  = rs1_valid_addr;
  assign rf_rs2_addr  = rs2_valid_addr;
  assign dec_rs1_addr = rs1_valid_addr;
  assign dec_rs2_addr = rs2_valid_addr;
  assign dec_rd_addr  = rd_valid_addr;
  assign dec_pc       = id_pc;
  assign dec_rs1_data = rf_rs1_data;
  assign dec_rs2_data = rf_rs2_data;

  // Immediate Generator
  always_comb begin
    case (opcode)
      OPCODE_OP_IMM,
      OPCODE_LOAD,
      OPCODE_JALR: begin
        imm = {{20{id_inst[31]}}, id_inst[31:20]};
      end

      OPCODE_STORE: begin
        imm = {{20{id_inst[31]}}, id_inst[31:25], id_inst[11:7]};
      end

      OPCODE_BRANCH: begin
        imm = {{19{id_inst[31]}}, id_inst[31], id_inst[7], id_inst[30:25], id_inst[11:8], 1'b0};
      end

      OPCODE_LUI,
      OPCODE_AUIPC: begin
        imm = {id_inst[31:12], 12'b0};
      end

      OPCODE_JAL: begin
        imm = {{11{id_inst[31]}}, id_inst[31], id_inst[19:12], id_inst[20], id_inst[30:21], 1'b0};
      end

      default: begin
        imm = 32'h0;
      end
    endcase
  end

  assign dec_imm = imm;

  // Control Unit
  always_comb begin
    dec_alu_op      = ALU_ADD;
    dec_alu_src_a   = ALU_SRC_A_RS1;
    dec_alu_src_b   = ALU_SRC_B_RS2;
    dec_branch_type = BR_NONE;
    dec_mem_read    = 1'b0;
    dec_mem_write   = 1'b0;
    dec_reg_write   = 1'b0;
    dec_wb_sel      = WB_SEL_ALU;

    case (opcode)
      OPCODE_OP: begin
        dec_alu_src_a = ALU_SRC_A_RS1;
        dec_alu_src_b = ALU_SRC_B_RS2;
        dec_reg_write = (rd_valid_addr != 5'd0);
        dec_wb_sel    = WB_SEL_ALU;
        case (funct3)
          3'b000: begin
            if (funct7[5]) dec_alu_op = ALU_SUB;
            else           dec_alu_op = ALU_ADD;
          end
          3'b001: dec_alu_op = ALU_SLL;
          3'b010: dec_alu_op = ALU_SLT;
          3'b011: dec_alu_op = ALU_SLTU;
          3'b100: dec_alu_op = ALU_XOR;
          3'b101: begin
            if (funct7[5]) dec_alu_op = ALU_SRA;
            else           dec_alu_op = ALU_SRL;
          end
          3'b110: dec_alu_op = ALU_OR;
          3'b111: dec_alu_op = ALU_AND;
          default: dec_alu_op = ALU_ADD;
        endcase
      end

      OPCODE_OP_IMM: begin
        dec_alu_src_a = ALU_SRC_A_RS1;
        dec_alu_src_b = ALU_SRC_B_IMM;
        dec_reg_write = (rd_valid_addr != 5'd0);
        dec_wb_sel    = WB_SEL_ALU;
        case (funct3)
          3'b000: dec_alu_op = ALU_ADD;
          3'b001: dec_alu_op = ALU_SLL;
          3'b010: dec_alu_op = ALU_SLT;
          3'b011: dec_alu_op = ALU_SLTU;
          3'b100: dec_alu_op = ALU_XOR;
          3'b101: begin
            if (funct7[5]) dec_alu_op = ALU_SRA;
            else           dec_alu_op = ALU_SRL;
          end
          3'b110: dec_alu_op = ALU_OR;
          3'b111: dec_alu_op = ALU_AND;
          default: dec_alu_op = ALU_ADD;
        endcase
      end

      OPCODE_LOAD: begin
        dec_alu_src_a = ALU_SRC_A_RS1;
        dec_alu_src_b = ALU_SRC_B_IMM;
        dec_alu_op    = ALU_ADD;
        dec_mem_read  = 1'b1;
        dec_reg_write = (rd_valid_addr != 5'd0);
        dec_wb_sel    = WB_SEL_MEM;
      end

      OPCODE_STORE: begin
        dec_alu_src_a = ALU_SRC_A_RS1;
        dec_alu_src_b = ALU_SRC_B_IMM;
        dec_alu_op    = ALU_ADD;
        dec_mem_write = 1'b1;
        dec_reg_write = 1'b0;
      end

      OPCODE_BRANCH: begin
        dec_alu_src_a   = ALU_SRC_A_PC;
        dec_alu_src_b   = ALU_SRC_B_IMM;
        dec_alu_op      = ALU_SUB;
        dec_reg_write   = 1'b0;
        case (funct3)
          3'b000: dec_branch_type = BR_BEQ;
          3'b001: dec_branch_type = BR_BNE;
          3'b100: dec_branch_type = BR_BLT;
          3'b101: dec_branch_type = BR_BGE;
          3'b100: dec_branch_type = BR_BLT;
          3'b101: dec_branch_type = BR_BGE;
          3'b110: dec_branch_type = BR_BLTU;
          3'b111: dec_branch_type = BR_BGEU;
          default: dec_branch_type = BR_NONE;
        endcase
      end

      OPCODE_LUI: begin
        dec_alu_src_a = ALU_SRC_A_RS1;
        dec_alu_src_b = ALU_SRC_B_IMM;
        dec_alu_op    = ALU_ADD;
        dec_reg_write = (rd_valid_addr != 5'd0);
        dec_wb_sel    = WB_SEL_ALU;
      end

      OPCODE_AUIPC: begin
        dec_alu_src_a = ALU_SRC_A_PC;
        dec_alu_src_b = ALU_SRC_B_IMM;
        dec_alu_op    = ALU_ADD;
        dec_reg_write = (rd_valid_addr != 5'd0);
        dec_wb_sel    = WB_SEL_ALU;
      end

      OPCODE_JAL: begin
        dec_alu_src_a = ALU_SRC_A_PC;
        dec_alu_src_b = ALU_SRC_B_IMM;
        dec_alu_op    = ALU_ADD;
        dec_reg_write = (rd_valid_addr != 5'd0);
        dec_wb_sel    = WB_SEL_PC4;
      end

      OPCODE_JALR: begin
        dec_alu_src_a = ALU_SRC_A_RS1;
        dec_alu_src_b = ALU_SRC_B_IMM;
        dec_alu_op    = ALU_ADD;
        dec_reg_write = (rd_valid_addr != 5'd0);
        dec_wb_sel    = WB_SEL_PC4;
      end

      default: begin
      end
    endcase
  end

endmodule : moola_decode

tb/tb_moola_decode.sv
//=============================================================================
// Project      : Moola-V (MR5) Core Verification
// File Name    : tb_moola_decode.sv
// Description  : Self-Checking Testbench for Instruction Decode & ImmGen
//=============================================================================

`timescale 1ns / 1ps

module tb_moola_decode;
  import moola_pkg::*;

  // DUT Inputs
  logic [31:0] id_pc;
  logic [31:0] id_pc_plus_4;
  logic [31:0] id_inst;
  logic [31:0] rf_rs1_data;
  logic [31:0] rf_rs2_data;

  // DUT Outputs (Flat signals - Icarus Verilog safe)
  logic [4:0]              rf_rs1_addr;
  logic [4:0]              rf_rs2_addr;
  logic [31:0]             dec_pc;
  logic [31:0]             dec_rs1_data;
  logic [31:0]             dec_rs2_data;
  logic [4:0]              dec_rs1_addr;
  logic [4:0]              dec_rs2_addr;
  logic [4:0]              dec_rd_addr;
  logic [31:0]             dec_imm;
  moola_pkg::alu_op_e      dec_alu_op;
  moola_pkg::alu_src_a_e   dec_alu_src_a;
  moola_pkg::alu_src_b_e   dec_alu_src_b;
  moola_pkg::branch_type_e dec_branch_type;
  logic                    dec_mem_read;
  logic                    dec_mem_write;
  logic                    dec_reg_write;
  moola_pkg::wb_sel_e      dec_wb_sel;

  // Tracking Counters
  int test_count  = 0;
  int error_count = 0;

  // -------------------------------------------------------------------------
  // DUT Instantiation
  // -------------------------------------------------------------------------
  moola_decode dut (
    .id_pc           (id_pc),
    .id_pc_plus_4    (id_pc_plus_4),
    .id_inst         (id_inst),
    .rf_rs1_data     (rf_rs1_data),
    .rf_rs2_data     (rf_rs2_data),
    .rf_rs1_addr     (rf_rs1_addr),
    .rf_rs2_addr     (rf_rs2_addr),
    .dec_pc          (dec_pc),
    .dec_rs1_data    (dec_rs1_data),
    .dec_rs2_data    (dec_rs2_data),
    .dec_rs1_addr    (dec_rs1_addr),
    .dec_rs2_addr    (dec_rs2_addr),
    .dec_rd_addr     (dec_rd_addr),
    .dec_imm         (dec_imm),
    .dec_alu_op      (dec_alu_op),
    .dec_alu_src_a   (dec_alu_src_a),
    .dec_alu_src_b   (dec_alu_src_b),
    .dec_branch_type (dec_branch_type),
    .dec_mem_read    (dec_mem_read),
    .dec_mem_write   (dec_mem_write),
    .dec_reg_write   (dec_reg_write),
    .dec_wb_sel      (dec_wb_sel)
  );

  initial begin
    $dumpfile("sim/decode_sim.vcd");
    $dumpvars(0, tb_moola_decode);
  end

  // -------------------------------------------------------------------------
  // Generic Check Task
  // -------------------------------------------------------------------------
  task check_decode(
    input logic [31:0] inst,
    input logic [31:0] pc,
    input logic [4:0]  exp_rs1,
    input logic [4:0]  exp_rs2,
    input logic [4:0]  exp_rd,
    input logic [31:0] exp_imm,
    input alu_op_e     exp_alu_op,
    input alu_src_a_e  exp_src_a,
    input alu_src_b_e  exp_src_b,
    input wb_sel_e     exp_wb_sel,
    input logic        exp_mem_read,
    input logic        exp_mem_write,
    input string       test_name
  );
    id_inst      = inst;
    id_pc        = pc;
    id_pc_plus_4 = pc + 4;
    rf_rs1_data  = 32'hAAAA_AAAA;
    rf_rs2_data  = 32'h5555_5555;
    #1; // Allow combinational logic to settle

    test_count++;

    if ((rf_rs1_addr !== exp_rs1) ||
        (rf_rs2_addr !== exp_rs2) ||
        (dec_rd_addr !== exp_rd) ||
        (dec_imm !== exp_imm) ||
        (dec_alu_op !== exp_alu_op) ||
        (dec_alu_src_a !== exp_src_a) ||
        (dec_alu_src_b !== exp_src_b) ||
        (dec_wb_sel !== exp_wb_sel) ||
        (dec_mem_read !== exp_mem_read) ||
        (dec_mem_write !== exp_mem_write)) begin
      $error("[FAIL] Test %02d: %s", test_count, test_name);
      $display("\tExpected: rs1=%0d, rs2=%0d, rd=%0d, imm=0x%08h, mem_r=%b, mem_w=%b",
               exp_rs1, exp_rs2, exp_rd, exp_imm, exp_mem_read, exp_mem_write);
      $display("\tGot:      rs1=%0d, rs2=%0d, rd=%0d, imm=0x%08h, mem_r=%b, mem_w=%b",
               rf_rs1_addr, rf_rs2_addr, dec_rd_addr, dec_imm, dec_mem_read, dec_mem_write);
      error_count++;
    end else begin
      $display("[PASS] Test %02d: %-38s (Imm: 0x%08h, rd: x%02d)", test_count, test_name, dec_imm, dec_rd_addr);
    end
  endtask

  // -------------------------------------------------------------------------
  // Test Stimulus Across Instruction Formats
  // -------------------------------------------------------------------------
  initial begin
    $display("\n========================================================");
    $display("     STARTING MOOLA-V DECODE & IMMGEN VERIFICATION      ");
    $display("========================================================\n");

    // 1. R-Type: ADD x3, x1, x2 (0x002081B3)
    check_decode(
      .inst          (32'h002081B3),
      .pc            (32'h8000_0000),
      .exp_rs1       (5'd1),
      .exp_rs2       (5'd2),
      .exp_rd        (5'd3),
      .exp_imm       (32'h0000_0000),
      .exp_alu_op    (ALU_ADD),
      .exp_src_a     (ALU_SRC_A_RS1),
      .exp_src_b     (ALU_SRC_B_RS2),
      .exp_wb_sel    (WB_SEL_ALU),
      .exp_mem_read  (1'b0),
      .exp_mem_write (1'b0),
      .test_name     ("R-Type: ADD x3, x1, x2")
    );

    // 2. I-Type (Arithmetic): ADDI x5, x1, -1 (0xFFF08293)
    check_decode(
      .inst          (32'hFFF08293),
      .pc            (32'h8000_0004),
      .exp_rs1       (5'd1),
      .exp_rs2       (5'd0),
      .exp_rd        (5'd5),
      .exp_imm       (32'hFFFF_FFFF),
      .exp_alu_op    (ALU_ADD),
      .exp_src_a     (ALU_SRC_A_RS1),
      .exp_src_b     (ALU_SRC_B_IMM),
      .exp_wb_sel    (WB_SEL_ALU),
      .exp_mem_read  (1'b0),
      .exp_mem_write (1'b0),
      .test_name     ("I-Type: ADDI x5, x1, -1 (Negative Imm)")
    );

    // 3. I-Type (Load): LW x6, 8(x1) (0x0080A303)
    check_decode(
      .inst          (32'h0080A303),
      .pc            (32'h8000_0008),
      .exp_rs1       (5'd1),
      .exp_rs2       (5'd0),
      .exp_rd        (5'd6),
      .exp_imm       (32'h0000_0008),
      .exp_alu_op    (ALU_ADD),
      .exp_src_a     (ALU_SRC_A_RS1),
      .exp_src_b     (ALU_SRC_B_IMM),
      .exp_wb_sel    (WB_SEL_MEM),
      .exp_mem_read  (1'b1),
      .exp_mem_write (1'b0),
      .test_name     ("I-Type Load: LW x6, 8(x1)")
    );

    // 4. S-Type (Store): SW x2, -4(x1) (0xFE20AE23)
    check_decode(
      .inst          (32'hFE20AE23),
      .pc            (32'h8000_000C),
      .exp_rs1       (5'd1),
      .exp_rs2       (5'd2),
      .exp_rd        (5'd0),
      .exp_imm       (32'hFFFF_FFFC),
      .exp_alu_op    (ALU_ADD),
      .exp_src_a     (ALU_SRC_A_RS1),
      .exp_src_b     (ALU_SRC_B_IMM),
      .exp_wb_sel    (WB_SEL_ALU),
      .exp_mem_read  (1'b0),
      .exp_mem_write (1'b1),
      .test_name     ("S-Type Store: SW x2, -4(x1)")
    );

    // 5. B-Type (Branch): BEQ x1, x2, -8 (0xFE208CE3)
    check_decode(
      .inst          (32'hFE208CE3),
      .pc            (32'h8000_0010),
      .exp_rs1       (5'd1),
      .exp_rs2       (5'd2),
      .exp_rd        (5'd0),
      .exp_imm       (32'hFFFF_FFF8),
      .exp_alu_op    (ALU_SUB),
      .exp_src_a     (ALU_SRC_A_PC),
      .exp_src_b     (ALU_SRC_B_IMM),
      .exp_wb_sel    (WB_SEL_ALU),
      .exp_mem_read  (1'b0),
      .exp_mem_write (1'b0),
      .test_name     ("B-Type Branch: BEQ x1, x2, -8")
    );

    // 6. U-Type: LUI x10, 0x12345 (0x12345537)
    check_decode(
      .inst          (32'h12345537),
      .pc            (32'h8000_0014),
      .exp_rs1       (5'd0),
      .exp_rs2       (5'd0),
      .exp_rd        (5'd10),
      .exp_imm       (32'h1234_5000),
      .exp_alu_op    (ALU_ADD),
      .exp_src_a     (ALU_SRC_A_RS1),
      .exp_src_b     (ALU_SRC_B_IMM),
      .exp_wb_sel    (WB_SEL_ALU),
      .exp_mem_read  (1'b0),
      .exp_mem_write (1'b0),
      .test_name     ("U-Type: LUI x10, 0x12345")
    );

    // 7. J-Type (Jump): JAL x1, -16 (0xFF1FF0EF)
    check_decode(
      .inst          (32'hFF1FF0EF),
      .pc            (32'h8000_0018),
      .exp_rs1       (5'd0),
      .exp_rs2       (5'd0),
      .exp_rd        (5'd1),
      .exp_imm       (32'hFFFF_FFF0),
      .exp_alu_op    (ALU_ADD),
      .exp_src_a     (ALU_SRC_A_PC),
      .exp_src_b     (ALU_SRC_B_IMM),
      .exp_wb_sel    (WB_SEL_PC4),
      .exp_mem_read  (1'b0),
      .exp_mem_write (1'b0),
      .test_name     ("J-Type Jump: JAL x1, -16")
    );

    // Summary Output
    $display("\n========================================================");
    if (error_count == 0) begin
      $display("  ALL %0d DECODE & IMMGEN TESTS PASSED SUCCESSFULLY!", test_count);
    end else begin
      $display("  DECODE VERIFICATION FAILED WITH %0d ERRORS.", error_count);
    end
    $display("========================================================\n");
    $finish;
  end

endmodule : tb_moola_decode

sim/decode_sim.vcd
$date
	Tue Sep  8 20:20:26 2026
$end
$version
	Icarus Verilog
$end
$timescale
	1ps
$end
$scope module tb_moola_decode $end
$var wire 5 ! rf_rs2_addr [4:0] $end
$var wire 5 " rf_rs1_addr [4:0] $end
$var wire 2 # dec_wb_sel [1:0] $end
$var wire 32 $ dec_rs2_data [31:0] $end
$var wire 5 % dec_rs2_addr [4:0] $end
$var wire 32 & dec_rs1_data [31:0] $end
$var wire 5 ' dec_rs1_addr [4:0] $end
$var wire 1 ( dec_reg_write $end
$var wire 5 ) dec_rd_addr [4:0] $end
$var wire 32 * dec_pc [31:0] $end
$var wire 1 + dec_mem_write $end
$var wire 1 , dec_mem_read $end
$var wire 32 - dec_imm [31:0] $end
$var wire 3 . dec_branch_type [2:0] $end
$var wire 1 / dec_alu_src_b $end
$var wire 1 0 dec_alu_src_a $end
$var wire 4 1 dec_alu_op [3:0] $end
$var reg 32 2 id_inst [31:0] $end
$var reg 32 3 id_pc [31:0] $end
$var reg 32 4 id_pc_plus_4 [31:0] $end
$var reg 32 5 rf_rs1_data [31:0] $end
$var reg 32 6 rf_rs2_data [31:0] $end
$var integer 32 7 error_count [31:0] $end
$var integer 32 8 test_count [31:0] $end
$scope module dut $end
$var wire 32 9 dec_imm [31:0] $end
$var wire 32 : dec_pc [31:0] $end
$var wire 5 ; dec_rd_addr [4:0] $end
$var wire 5 < dec_rs1_addr [4:0] $end
$var wire 32 = dec_rs1_data [31:0] $end
$var wire 5 > dec_rs2_addr [4:0] $end
$var wire 32 ? dec_rs2_data [31:0] $end
$var wire 32 @ id_inst [31:0] $end
$var wire 32 A id_pc [31:0] $end
$var wire 32 B id_pc_plus_4 [31:0] $end
$var wire 5 C rf_rs1_addr [4:0] $end
$var wire 32 D rf_rs1_data [31:0] $end
$var wire 5 E rf_rs2_addr [4:0] $end
$var wire 32 F rf_rs2_data [31:0] $end
$var wire 5 G rs2_raw [4:0] $end
$var wire 5 H rs1_raw [4:0] $end
$var wire 5 I rd_raw [4:0] $end
$var wire 7 J opcode [6:0] $end
$var wire 7 K funct7 [6:0] $end
$var wire 3 L funct3 [2:0] $end
$var reg 4 M dec_alu_op [3:0] $end
$var reg 1 0 dec_alu_src_a $end
$var reg 1 / dec_alu_src_b $end
$var reg 3 N dec_branch_type [2:0] $end
$var reg 1 , dec_mem_read $end
$var reg 1 + dec_mem_write $end
$var reg 1 ( dec_reg_write $end
$var reg 2 O dec_wb_sel [1:0] $end
$var reg 32 P imm [31:0] $end
$var reg 5 Q rd_valid_addr [4:0] $end
$var reg 5 R rs1_valid_addr [4:0] $end
$var reg 5 S rs2_valid_addr [4:0] $end
$upscope $end
$scope task check_decode $end
$var reg 4 T exp_alu_op [3:0] $end
$var reg 32 U exp_imm [31:0] $end
$var reg 1 V exp_mem_read $end
$var reg 1 W exp_mem_write $end
$var reg 5 X exp_rd [4:0] $end
$var reg 5 Y exp_rs1 [4:0] $end
$var reg 5 Z exp_rs2 [4:0] $end
$var reg 1 [ exp_src_a $end
$var reg 1 \ exp_src_b $end
$var reg 2 ] exp_wb_sel [1:0] $end
$var reg 32 ^ inst [31:0] $end
$var reg 32 _ pc [31:0] $end
$upscope $end
$upscope $end
$enddefinitions $end
$comment Show the parameter values. $end
$dumpall
$end
#0
$dumpvars
b10000000000000000000000000000000 _
b1000001000000110110011 ^
b0 ]
0\
0[
b10 Z
b1 Y
b11 X
0W
0V
b0 U
b0 T
b10 S
b1 R
b11 Q
b0 P
b0 O
b10 N
b0 M
b0 L
b0 K
b110011 J
b11 I
b1 H
b10 G
b1010101010101010101010101010101 F
b10 E
b10101010101010101010101010101010 D
b1 C
b10000000000000000000000000000100 B
b10000000000000000000000000000000 A
b1000001000000110110011 @
b1010101010101010101010101010101 ?
b10 >
b10101010101010101010101010101010 =
b1 <
b11 ;
b10000000000000000000000000000000 :
b0 9
b0 8
b0 7
b1010101010101010101010101010101 6
b10101010101010101010101010101010 5
b10000000000000000000000000000100 4
b10000000000000000000000000000000 3
b1000001000000110110011 2
b0 1
00
0/
b10 .
b0 -
0,
0+
b10000000000000000000000000000000 *
b11 )
1(
b1 '
b10101010101010101010101010101010 &
b10 %
b1010101010101010101010101010101 $
b0 #
b1 "
b10 !
$end
#1000
b101 )
b101 ;
b101 Q
b0 %
b0 >
b0 !
b0 E
b0 S
1/
1(
b11111111111111111111111111111111 -
b11111111111111111111111111111111 9
b11111111111111111111111111111111 P
b10011 J
b101 I
b11111 G
b1111111 K
b10000000000000000000000000001000 4
b10000000000000000000000000001000 B
b10000000000000000000000000000100 *
b10000000000000000000000000000100 :
b10000000000000000000000000000100 3
b10000000000000000000000000000100 A
b11111111111100001000001010010011 2
b11111111111100001000001010010011 @
1\
b11111111111111111111111111111111 U
b101 X
b0 Z
b10000000000000000000000000000100 _
b11111111111100001000001010010011 ^
b1 8
#2000
b110 )
b110 ;
b110 Q
b1 #
b1 O
1,
1(
1/
b1000 -
b1000 9
b1000 P
b11 J
b110 I
b10 L
b1000 G
b0 K
b10000000000000000000000000001100 4
b10000000000000000000000000001100 B
b10000000000000000000000000001000 *
b10000000000000000000000000001000 :
b10000000000000000000000000001000 3
b10000000000000000000000000001000 A
b100000001010001100000011 2
b100000001010001100000011 @
1V
b1 ]
b1000 U
b110 X
b10000000000000000000000000001000 _
b100000001010001100000011 ^
b10 8
#3000
b0 )
b0 ;
b0 Q
b10 %
b10 >
b10 !
b10 E
b10 S
1+
b0 #
b0 O
0(
0,
1/
b11111111111111111111111111111100 -
b11111111111111111111111111111100 9
b11111111111111111111111111111100 P
b100011 J
b11100 I
b10 G
b1111111 K
b10000000000000000000000000010000 4
b10000000000000000000000000010000 B
b10000000000000000000000000001100 *
b10000000000000000000000000001100 :
b10000000000000000000000000001100 3
b10000000000000000000000000001100 A
b11111110001000001010111000100011 2
b11111110001000001010111000100011 @
1W
0V
b0 ]
b11111111111111111111111111111100 U
b0 X
b10 Z
b10000000000000000000000000001100 _
b11111110001000001010111000100011 ^
b11 8
#4000
b0 .
b0 N
b1 1
b1 M
10
0+
1/
b11111111111111111111111111111000 -
b11111111111111111111111111111000 9
b11111111111111111111111111111000 P
b1100011 J
b11001 I
b0 L
b10000000000000000000000000010100 4
b10000000000000000000000000010100 B
b10000000000000000000000000010000 *
b10000000000000000000000000010000 :
b10000000000000000000000000010000 3
b10000000000000000000000000010000 A
b11111110001000001000110011100011 2
b11111110001000001000110011100011 @
0W
1[
b1 T
b11111111111111111111111111111000 U
b10000000000000000000000000010000 _
b11111110001000001000110011100011 ^
b100 8
#5000
1(
b1010 )
b1010 ;
b1010 Q
b0 %
b0 >
b0 !
b0 E
b0 S
b0 '
b0 <
b0 "
b0 C
b0 R
b10 .
b10 N
1/
00
b0 1
b0 M
b10010001101000101000000000000 -
b10010001101000101000000000000 9
b10010001101000101000000000000 P
b110111 J
b1010 I
b101 L
b1000 H
b11 G
b1001 K
b10000000000000000000000000011000 4
b10000000000000000000000000011000 B
b10000000000000000000000000010100 *
b10000000000000000000000000010100 :
b10000000000000000000000000010100 3
b10000000000000000000000000010100 A
b10010001101000101010100110111 2
b10010001101000101010100110111 @
0[
b0 T
b10010001101000101000000000000 U
b1010 X
b0 Z
b0 Y
b10000000000000000000000000010100 _
b10010001101000101010100110111 ^
b101 8
#6000
b1 )
b1 ;
b1 Q
b10 #
b10 O
10
1(
1/
b11111111111111111111111111110000 -
b11111111111111111111111111110000 9
b11111111111111111111111111110000 P
b1101111 J
b1 I
b111 L
b11111 H
b10001 G
b1111111 K
b10000000000000000000000000011100 4
b10000000000000000000000000011100 B
b10000000000000000000000000011000 *
b10000000000000000000000000011000 :
b10000000000000000000000000011000 3
b10000000000000000000000000011000 A
b11111111000111111111000011101111 2
b11111111000111111111000011101111 @
b10 ]
1[
b11111111111111111111111111110000 U
b1 X
b10000000000000000000000000011000 _
b11111111000111111111000011101111 ^
b110 8
#7000
b111 8
