rtl/moola_regfile.sv
//=============================================================================
// Project      : Moola-V (MR5) Core
// File Name    : moola_regfile.sv
// Description  : 32x32-bit General Purpose Register File with x0=0 & WB Bypass
//=============================================================================

`timescale 1ns / 1ps

module moola_regfile (
  input  logic        clk,
  input  logic        rst_n,

  // Read Ports (Asynchronous / Combinational)
  input  logic [4:0]  rs1_addr,
  output logic [31:0] rs1_data,

  input  logic [4:0]  rs2_addr,
  output logic [31:0] rs2_data,

  // Write Port from Write-Back Stage (Synchronous)
  input  logic        reg_write,
  input  logic [4:0]  rd_addr,
  input  logic [31:0] rd_data
);

  logic [31:0] regs [31:0];

  // Synchronous Write (x0 is hardwired to 0)
  always_ff @(posedge clk or negedge rst_n) begin
    if (!rst_n) begin
      for (int i = 0; i < 32; i++) begin
        regs[i] <= 32'h0;
      end
    end else if (reg_write && (rd_addr != 5'd0)) begin
      regs[rd_addr] <= rd_data;
    end
  end

  // Read Port 1 with Write-Through Bypass
  always_comb begin
    if (rs1_addr == 5'd0) begin
      rs1_data = 32'h0;
    end else if (reg_write && (rd_addr == rs1_addr)) begin
      rs1_data = rd_data; // Internal bypass when writing and reading same register
    end else begin
      rs1_data = regs[rs1_addr];
    end
  end

  // Read Port 2 with Write-Through Bypass
  always_comb begin
    if (rs2_addr == 5'd0) begin
      rs2_data = 32'h0;
    end else if (reg_write && (rd_addr == rs2_addr)) begin
      rs2_data = rd_data; // Internal bypass when writing and reading same register
    end else begin
      rs2_data = regs[rs2_addr];
    end
  end

endmodule : moola_regfile

tb/tb_moola_regfile.sv
//=============================================================================
// Project      : Moola-V (MR5) Core Verification
// File Name    : tb_moola_regfile.sv
// Description  : Self-Checking Testbench for Register File (x0 & Internal Bypass)
//=============================================================================

`timescale 1ns / 1ps

module tb_moola_regfile;

  logic        clk;
  logic        rst_n;

  logic [4:0]  rs1_addr;
  logic [31:0] rs1_data;

  logic [4:0]  rs2_addr;
  logic [31:0] rs2_data;

  logic        reg_write;
  logic [4:0]  rd_addr;
  logic [31:0] rd_data;

  int error_count = 0;

  // Instantiate DUT
  moola_regfile dut (
    .clk       (clk),
    .rst_n     (rst_n),
    .rs1_addr  (rs1_addr),
    .rs1_data  (rs1_data),
    .rs2_addr  (rs2_addr),
    .rs2_data  (rs2_data),
    .reg_write (reg_write),
    .rd_addr   (rd_addr),
    .rd_data   (rd_data)
  );

  initial begin
        $dumpfile("sim/regfile_sim.vcd");
        $dumpvars(0, tb_moola_regfile);
    end 

  // Clock Generation (100 MHz)
  always #5 clk = ~clk;

  initial begin
    clk       = 0;
    rst_n     = 0;
    rs1_addr  = 0;
    rs2_addr  = 0;
    reg_write = 0;
    rd_addr   = 0;
    rd_data   = 0;

    // Reset sequence
    #20 rst_n = 1;
    #10;

    $display("\n--- TEST 1: Write and Read General Purpose Registers (x1, x2) ---");
    @(negedge clk);
    reg_write = 1; rd_addr = 5'd1; rd_data = 32'hDEAD_BEEF;
    @(negedge clk);
    reg_write = 1; rd_addr = 5'd2; rd_data = 32'hCAFE_BABE;
    @(negedge clk);
    reg_write = 0;

    // Read back
    rs1_addr = 5'd1;
    rs2_addr = 5'd2;
    #1;
    if (rs1_data !== 32'hDEAD_BEEF || rs2_data !== 32'hCAFE_BABE) begin
      $error("[FAIL] Reg Read Mismatch: x1=0x%08h, x2=0x%08h", rs1_data, rs2_data);
      error_count++;
    end else begin
      $display("[PASS] Read x1=0x%08h, x2=0x%08h", rs1_data, rs2_data);
    end

    $display("\n--- TEST 2: Hardwired x0 Invariance Check ---");
    @(negedge clk);
    reg_write = 1; rd_addr = 5'd0; rd_data = 32'hFFFF_FFFF; // Attempt overwrite x0
    @(negedge clk);
    reg_write = 0;
    rs1_addr = 5'd0;
    #1;
    if (rs1_data !== 32'h0) begin
      $error("[FAIL] x0 was modified! Got: 0x%08h", rs1_data);
      error_count++;
    end else begin
      $display("[PASS] x0 remains hardwired to 0x00000000 after write attempt.");
    end

    $display("\n--- TEST 3: Same-Cycle Write-Through Bypass Check ---");
    @(negedge clk);
    // Write to x3 and read from x3 simultaneously
    reg_write = 1; rd_addr = 5'd3; rd_data = 32'h1234_5678;
    rs1_addr  = 5'd3;
    #1;
    if (rs1_data !== 32'h1234_5678) begin
      $error("[FAIL] Write-through bypass failed! Got: 0x%08h, Expected: 0x12345678", rs1_data);
      error_count++;
    end else begin
      $display("[PASS] Same-cycle bypass successful: x3 read 0x%08h combinationally.", rs1_data);
    end

    @(negedge clk);
    reg_write = 0;

    $display("\n========================================================");
    if (error_count == 0) $display("  ALL REGFILE UNIT TESTS PASSED!");
    else                  $display("  REGFILE TESTS FAILED WITH %0d ERRORS.", error_count);
    $display("========================================================\n");
    $finish;
  end

endmodule : tb_moola_regfile

sim/regfile_sim.vcd
$date
	Tue Sep  8 20:21:15 2026
$end
$version
	Icarus Verilog
$end
$timescale
	1ps
$end
$scope module tb_moola_regfile $end
$var wire 32 ! rs2_data [31:0] $end
$var wire 32 " rs1_data [31:0] $end
$var reg 1 # clk $end
$var reg 5 $ rd_addr [4:0] $end
$var reg 32 % rd_data [31:0] $end
$var reg 1 & reg_write $end
$var reg 5 ' rs1_addr [4:0] $end
$var reg 5 ( rs2_addr [4:0] $end
$var reg 1 ) rst_n $end
$var integer 32 * error_count [31:0] $end
$scope module dut $end
$var wire 1 # clk $end
$var wire 5 + rd_addr [4:0] $end
$var wire 32 , rd_data [31:0] $end
$var wire 1 & reg_write $end
$var wire 5 - rs1_addr [4:0] $end
$var wire 5 . rs2_addr [4:0] $end
$var wire 1 ) rst_n $end
$var reg 32 / rs1_data [31:0] $end
$var reg 32 0 rs2_data [31:0] $end
$scope begin $ivl_for_loop0 $end
$var integer 32 1 i [31:0] $end
$upscope $end
$upscope $end
$upscope $end
$enddefinitions $end
$comment Show the parameter values. $end
$dumpall
$end
#0
$dumpvars
b100000 1
b0 0
b0 /
b0 .
b0 -
b0 ,
b0 +
b0 *
0)
b0 (
b0 '
0&
b0 %
b0 $
0#
b0 "
b0 !
$end
#5000
b100000 1
1#
#10000
0#
#15000
b100000 1
1#
#20000
0#
1)
#25000
1#
#30000
b11011110101011011011111011101111 %
b11011110101011011011111011101111 ,
b1 $
b1 +
1&
0#
#35000
1#
#40000
b11001010111111101011101010111110 %
b11001010111111101011101010111110 ,
b10 $
b10 +
0#
#45000
1#
#50000
b11001010111111101011101010111110 !
b11001010111111101011101010111110 0
b11011110101011011011111011101111 "
b11011110101011011011111011101111 /
b10 (
b10 .
b1 '
b1 -
0&
0#
#55000
1#
#60000
b11111111111111111111111111111111 %
b11111111111111111111111111111111 ,
b0 $
b0 +
1&
0#
#65000
1#
#70000
b0 "
b0 /
b0 '
b0 -
0&
0#
#75000
1#
#80000
b10010001101000101011001111000 "
b10010001101000101011001111000 /
b11 '
b11 -
b10010001101000101011001111000 %
b10010001101000101011001111000 ,
b11 $
b11 +
1&
0#
#85000
1#
#90000
0&
0#
